LYMPHATIC/LYMPHATIC.HTML
LYMPHATIC/STUDIES.py
LYMPHATIC/__init__.py
LYMPHATIC/CYTE/CLIQUE_GROUP.py
LYMPHATIC/CYTE/CREATE.py
LYMPHATIC/CYTE/DROP.py
LYMPHATIC/CYTE/LIST.py
LYMPHATIC/CYTE/RENAME.py
LYMPHATIC/CYTE/STUDIES.HTML
LYMPHATIC/CYTE/RETHINKDB/HYGIENE.HTML
LYMPHATIC/CYTE/RETHINKDB/SERVER_CONFIG/REMOVE_DEFAULT_TAG.py
LYMPHATIC/CYTE/RETHINKDB/SERVER_CONFIG/RENAME_SERVER.py
LYMPHATIC/MOLECULE/INSERT_EPISODE.py
LYMPHATIC/NODE/CONNECT.py
LYMPHATIC/NODE/MULTI.py
LYMPHATIC/NODE/NODE.HTML
LYMPHATIC/NODE/__init__.py
LYMPHATIC/NODE/DATA/EXPORT.py
LYMPHATIC/NODE/DATA/IMPORT.py
LYMPHATIC/NODE/PROXY/PROXY.HTML
LYMPHATIC/ORGANELLE/CONFIG.py
LYMPHATIC/ORGANELLE/CREATE.py
LYMPHATIC/ORGANELLE/LIST.py
LYMPHATIC/ORGANELLE/RECONFIGURE.py
LYMPHATIC/ORGANELLE/RENAME.py
LYMPHATIC/ORGANELLE/PRIMARY_INDEX/PRIMARY_INDEX.HTML
LYMPHATIC/ORGANELLE/SECONDARY_INDEX/HYGIENE.HTML
LYMPHATIC/SYSTEM/SYSTEM.HTML
LYMPHATIC/SYSTEM/__init__.py
lymphaticdb-0.0.5.dist-info/METADATA
lymphaticdb-0.0.5.dist-info/WHEEL
lymphaticdb-0.0.5.dist-info/entry_points.txt
lymphaticdb-0.0.5.dist-info/top_level.txt
lymphaticdb-0.0.5.dist-info/RECORD
