Metadata-Version: 2.1
Name: lymphaticdb
Version: 0.0.5
Summary: The cybernetic immune system hyper drive of the inter-ellipitic navigator.
Requires-Dist: rethinkdb
Requires-Dist: BOTANIST
